{
  "abc7news.com": 20.0,
  "admiddleeast.com": 0.3,
  "airbnb.com": 550.0,
  "amazingarchitecture.com": 0.5,
  "aol.com": 180.0,
  "archaeologymag.com": 0.8,
  "architectureadrenaline.com": 0.1,
  "architizer.com": 3.5,
  "beinsure.com": 0.3,
  "biggerpockets.com": 8.0,
  "briefglance.com": 0.1,
  "british broadcasting corporation": 700.0,
  "builtechcg.com": 0.05,
  "californiacontractorinsurance.com": 0.05,
  "calsociety.com": 0.1,
  "canyon news": 0.2,
  "cappuccinoinsurance.com": 0.1,
  "carbondaleconstruction.ca": 0.05,
  "casaindonesia.com": 0.3,
  "ccr-mag.com": 0.15,
  "cginsurancesb.com": 0.05,
  "christiesresocal.com": 0.05,
  "clearsurance.com": 0.15,
  "constructionspecifier.com": 0.2,
  "consumerwatchdog.org": 0.3,
  "contemporist.com": 1.2,
  "cowboystatedaily.com": 2.0,
  "d5mag.com": 0.1,
  "dailymail.com": 15.0,
  "danleighhomes.com": 0.02,
  "davisvanguard.org": 0.2,
  "dig-in.com": 0.3,
  "domain.com.au": 30.0,
  "dupontregistry.com": 1.2,
  "durabondfencing.com": 0.05,
  "e-a-a.com": 0.1,
  "earth911.com": 1.0,
  "eastructuralengineering.com": 0.05,
  "eciks.org": 0.1,
  "economiccollapse.report": 0.1,
  "ecostarllc.com": 0.1,
  "edhat.com": 0.3,
  "eenews.net": 1.5,
  "einnews.com": 4.0,
  "elphaformwork.com": 0.05,
  "emberprousa.com": 0.05,
  "en.bd-pratidin.com": 1.5,
  "entertainmentnow.com": 0.3,
  "expansion.com": 25.0,
  "fbia.com": 0.05,
  "fireandsafetyjournalamericas.com": 0.1,
  "firerescue1.com": 1.2,
  "firerisk.ai": 0.1,
  "fox21online.com": 0.7,
  "galerie-philia.com": 0.1,
  "gemini search": 0.1,
  "geramiarchitecture.com": 0.1,
  "getty.edu": 4.5,
  "gjsentinel.com": 0.6,
  "globest.com": 1.2,
  "gov.ca.gov": 2.5,
  "greenhomebuildermag.com": 0.05,
  "guidewire.com": 1.5,
  "hanodecor.com": 0.1,
  "havenlifestyles.com": 0.1,
  "helencummins.com": 0.15,
  "hindustantimes.com": 180.0,
  "homesandgardens.com": 12.0,
  "hoodline.com": 2.5,
  "hoog.design": 0.2,
  "hospitalitynet.org": 1.2,
  "independent.com": 0.3,
  "insurancebusinessmag.com": 2.5,
  "insuranceforgood.org": 0.05,
  "insurancenewsnet.com": 0.5,
  "interiordesign.net": 2.5,
  "interlockroofing.com": 0.1,
  "joycerey.com": 0.05,
  "kqed.org": 6.0,
  "krcrtv.com": 2.5,
  "ktbs.com": 0.8,
  "ktvu.com": 3.0,
  "larchmontbuzz.com": 0.1,
  "latentinsure.com": 0.05,
  "laurabrauestates.com": 0.05,
  "lendingtree.com": 12.0,
  "liveinsurancenews.com": 0.1,
  "lrecompanies.com": 0.05,
  "luxurylaunches.com": 1.2,
  "malibutimes.com": 0.15,
  "marketscreener.com": 25.0,
  "matthewekahn.substack.com": 0.05,
  "maverickframe.com": 0.1,
  "meganmicco.com": 0.05,
  "mercurynews.com": 25.0,
  "moomoo.com": 15.0,
  "movoto.com": 8.0,
  "myvilla.la": 0.03,
  "nbcnews.com": 350.0,
  "newhousebuilder.com": 0.05,
  "newsweek.com": 100.0,
  "nickiandkaren.com": 0.1,
  "noncombustiblesllc.com": 0.05,
  "oakviewins.com": 0.05,
  "ocregister.com": 8.0,
  "oftmw.com": 0.1,
  "oldharbor.com": 0.05,
  "ownluxuryhomes.com": 0.05,
  "palipost.com": 0.05,
  "parametric-architecture.com": 1.2,
  "parriva.com": 0.1,
  "patriotmaids.com": 0.1,
  "prefab.com": 0.3,
  "programbusiness.com": 0.1,
  "propertyguardian.com": 0.1,
  "propertyinsurancecoveragelaw.com": 0.15,
  "pwdecor.com": 0.1,
  "qualityspace.com": 0.1,
  "rightmove.co.uk": 90.0,
  "ruthelia.com": 0.05,
  "santacruzsentinel.com": 2.5,
  "shenrealty.com": 0.1,
  "sierrasun.com": 0.3,
  "smarttechinvest.com": 0.1,
  "smdp.com": 0.3,
  "substack.com": 95.0,
  "superformicf.com": 0.15,
  "thealligoodgroup.com": 0.05,
  "theguardian.com": 390.0,
  "theoutragedconsumer.com": 0.05,
  "theunion.com": 0.4,
  "tmz.com": 60.0,
  "tollbrothers.com": 3.5,
  "topconsumerreviews.com": 2.0,
  "totaldesign.it": 0.1,
  "travelandleisureasia.com": 1.5,
  "travelbinger.com": 0.2,
  "unitedroofingcalifornia.com": 0.05,
  "uphelp.org": 0.15,
  "usatoday.com": 160.0,
  "vanityfair.com": 45.0,
  "voterguide.sos.ca.gov": 0.3,
  "washingtonmonthly.com": 0.8,
  "western-wildfire-defense.com": 0.05,
  "westsidetoday.com": 0.15,
  "whins.com": 0.05,
  "wildfiresafetysystems.com": 0.05,
  "worldjournal.com": 3.0,
  "yankodesign.com": 4.0,
  "youngdouglasinsurance.com": 0.05,
  "yubanet.com": 0.3
}